{
  "hideStrictPathFilters": true,
  "pinFilters": {
    "active": true,
    "tags": [
      {
        "name": "",
        "active": true,
        "pattern": "",
        "patternType": "STRICT"
      }
    ],
    "paths": [
      {
        "name": "hooks",
        "active": true,
        "type": "FILES_AND_DIRECTORIES",
        "pattern": "hooks",
        "patternType": "WILDCARD"
      },
      {
        "name": "",
        "active": true,
        "type": "FILES_AND_DIRECTORIES",
        "pattern": "",
        "patternType": "WILDCARD"
      }
    ]
  },
  "hideFilters": {
    "active": false,
    "tags": [
      {
        "name": "",
        "active": true,
        "pattern": "",
        "patternType": "STRICT"
      }
    ],
    "paths": [
      {
        "name": "",
        "active": true,
        "type": "DIRECTORIES",
        "pattern": "hooks",
        "patternType": "STRICT"
      },
      {
        "name": "",
        "active": true,
        "type": "DIRECTORIES",
        "pattern": "lib",
        "patternType": "STRICT"
      },
      {
        "name": "",
        "active": true,
        "type": "DIRECTORIES",
        "pattern": "layouts",
        "patternType": "STRICT"
      },
      {
        "name": "",
        "active": true,
        "type": "DIRECTORIES",
        "pattern": "icons",
        "patternType": "STRICT"
      },
      {
        "name": "",
        "active": true,
        "type": "DIRECTORIES",
        "pattern": "config",
        "patternType": "STRICT"
      },
      {
        "name": "",
        "active": true,
        "type": "DIRECTORIES",
        "pattern": "components",
        "patternType": "STRICT"
      },
      {
        "name": "",
        "active": true,
        "type": "DIRECTORIES",
        "pattern": "types",
        "patternType": "STRICT"
      },
      {
        "name": "",
        "active": true,
        "type": "FILES",
        "pattern": "env.d.ts",
        "patternType": "STRICT"
      },
      {
        "name": "",
        "active": true,
        "type": "DIRECTORIES",
        "pattern": "dist",
        "patternType": "STRICT"
      },
      {
        "name": "",
        "active": true,
        "type": "DIRECTORIES",
        "pattern": "node_modules",
        "patternType": "STRICT"
      },
      {
        "name": "",
        "active": true,
        "type": "FILES",
        "pattern": "src/env.d.ts",
        "patternType": "STRICT"
      }
    ]
  }
}